.gitignore
.pre-commit-config.yaml
LICENSE
MANIFEST.in
README.md
coindicator.desktop
install.sh
pyproject.toml
requirements.txt
setup.cfg
setup.py
img/gitcoin.png
img/screenshot.png
src/coin/__init__.py
src/coin/about.py
src/coin/alarm.py
src/coin/asset_selection.py
src/coin/coin.py
src/coin/coingecko_client.py
src/coin/config.py
src/coin/config.yaml
src/coin/downloader.py
src/coin/error.py
src/coin/exchange.py
src/coin/indicator.py
src/coin/plugin_selection.py
src/coin/exchanges/binance.py
src/coin/exchanges/bitfinex.py
src/coin/exchanges/bitkub.py
src/coin/exchanges/bitstamp.py
src/coin/exchanges/bittrex.py
src/coin/exchanges/cexio.py
src/coin/exchanges/gemini.py
src/coin/exchanges/hitbtc.py
src/coin/exchanges/kraken.py
src/coin/exchanges/okcoin.py
src/coin/exchanges/poloniex.py
src/coin/exchanges/unocoin.py
src/coin/resources/ca-ching.wav
src/coin/resources/icon.png
src/coin/resources/icon_32px.png
src/coin/resources/icon_48px.png
src/coin/resources/icon_64px.png
src/coin/resources/loading.png
src/coin/resources/logo_124px.png
src/coin/resources/logo_124pxs.png
src/coin/resources/logo_248px.png
src/coindicator.egg-info/PKG-INFO
src/coindicator.egg-info/SOURCES.txt
src/coindicator.egg-info/dependency_links.txt
src/coindicator.egg-info/entry_points.txt
src/coindicator.egg-info/not-zip-safe
src/coindicator.egg-info/requires.txt
src/coindicator.egg-info/top_level.txt