Metadata-Version: 2.1
Name: coindicator
Version: 2.1.4
Summary: Coinprice Indicator
Home-page: https://github.com/bluppfisk/coindicator/
Author: Sander Van de Moortel
Author-email: sander.vandemoortel@gmail.com
License: MIT
Project-URL: Documentation, https://github.com/bluppfisk/coindicator/
Platform: Linux
Classifier: Development Status :: 5 - Production/Stable
Classifier: Programming Language :: Python
Provides-Extra: develop
License-File: LICENSE
